ml2json/__init__.py
ml2json/applicability_domain.py
ml2json/classification.py
ml2json/cluster.py
ml2json/cross_decomposition.py
ml2json/decomposition.py
ml2json/feature_extraction.py
ml2json/manifold.py
ml2json/ml2json.py
ml2json/neighbors.py
ml2json/over_undersampling.py
ml2json/pipeline.py
ml2json/preprocessing.py
ml2json/regression.py
ml2json/utils/__init__.py
ml2json/utils/bunch.py
ml2json/utils/csr.py
ml2json/utils/memory.py
ml2json/utils/random_state.py
ml2json-0.5.1.dist-info/licenses/LICENSE
ml2json-0.5.1.dist-info/METADATA
ml2json-0.5.1.dist-info/WHEEL
ml2json-0.5.1.dist-info/top_level.txt
ml2json-0.5.1.dist-info/RECORD
