Metadata-Version: 2.4
Name: ml2json
Version: 0.5.1
Summary: A safe, transparent way to share and deploy scikit-learn models.
Home-page: https://github.com/OlivierBeq/ml2json
Author: Mathieu Rodrigue
Author-email: support@mlrequest.com
Maintainer: Olivier J.M. Béquignon
Maintainer-email: olivier.bequignon.maintainer@gmail.com
License: MIT
Keywords: scikit-learn,serializing,json,reproducibility,machine learning
Classifier: Programming Language :: Python
Classifier: Programming Language :: Python :: 3
Classifier: Programming Language :: Python :: 3.9
Classifier: Programming Language :: Python :: 3.8
Classifier: Programming Language :: Python :: 3.7
Classifier: Programming Language :: Python :: 3.6
Classifier: License :: OSI Approved :: MIT License
Classifier: Operating System :: OS Independent
License-File: LICENSE
Requires-Dist: scikit-learn<=1.4.0,>=1.2.2
Requires-Dist: scipy
Requires-Dist: joblib
Provides-Extra: full
Requires-Dist: xgboost>=2.0.3; extra == "full"
Requires-Dist: lightgbm; extra == "full"
Requires-Dist: catboost; extra == "full"
Requires-Dist: hdbscan; extra == "full"
Requires-Dist: pynndescent; extra == "full"
Requires-Dist: umap-learn; extra == "full"
Requires-Dist: kmodes; extra == "full"
Requires-Dist: mlchemad>=1.5.0; extra == "full"
Requires-Dist: hnswlib; extra == "full"
Requires-Dist: opentsne; extra == "full"
Requires-Dist: imblearn; extra == "full"
Provides-Extra: docs
Requires-Dist: sphinx; extra == "docs"
Requires-Dist: sphinx-rtd-theme; extra == "docs"
Requires-Dist: sphinx-autodoc-typehints; extra == "docs"
Provides-Extra: testing
Requires-Dist: pytest; extra == "testing"
Dynamic: license-file
